crypto_vault/__init__.py
crypto_vault/abi.json
crypto_vault/config.py
crypto_vault/crypto_vault.py
crypto_vault/encryption.py
crypto_vault-0.1.1.dist-info/LICENSE
crypto_vault-0.1.1.dist-info/METADATA
crypto_vault-0.1.1.dist-info/WHEEL
crypto_vault-0.1.1.dist-info/top_level.txt
crypto_vault-0.1.1.dist-info/RECORD
