Metadata-Version: 2.1
Name: crypto-vault
Version: 0.1.1
Summary: Efficiently encrypt data off-chain and store securely on the blockchain
Home-page: https://github.com/allelementary/crypto-vault-off-chain
Author: Mikhail Antonov
Author-email: allelementaryfor@gmail.com
Classifier: Programming Language :: Python :: 3
Classifier: Programming Language :: Python :: 3.9
Classifier: License :: OSI Approved :: MIT License
Classifier: Development Status :: 3 - Alpha
Classifier: Intended Audience :: Developers
Classifier: Topic :: Software Development :: Libraries :: Python Modules
Classifier: Operating System :: OS Independent
License-File: LICENSE
Requires-Dist: cryptography ==42.0.5
Requires-Dist: pydantic ==2.6.4
Requires-Dist: web3 ==6.15.1
